bratevalwrapper4nlp/__init__.py
bratevalwrapper4nlp/evaluate.py
bratevalwrapper4nlp/io.py
bratevalwrapper4nlp/wrapper.py
bratevalwrapper4nlp-0.0.2.dist-info/LICENSE
bratevalwrapper4nlp-0.0.2.dist-info/METADATA
bratevalwrapper4nlp-0.0.2.dist-info/WHEEL
bratevalwrapper4nlp-0.0.2.dist-info/top_level.txt
bratevalwrapper4nlp-0.0.2.dist-info/RECORD
