Metadata-Version: 2.1
Name: bratevalwrapper4nlp
Version: 0.0.2
Summary: A small wrapper for BratEval that encapsulates the java commands
Author-email: Johann Frei <johann_frei@yahoo.de>
Project-URL: Homepage, https://github.com/j-frei/BratEvalWrapper4NLP
Project-URL: Issues, https://github.com/j-frei/BratEvalWrapper4NLP/issues
Classifier: Programming Language :: Python :: 3
Classifier: License :: OSI Approved :: MIT License
Classifier: Operating System :: OS Independent
Classifier: Topic :: Scientific/Engineering
Classifier: Topic :: Text Processing
Requires-Python: >=3.8
License-File: LICENSE
